README.md
setup.py
active_directory/__init__.py
active_directory/abstract.py
active_directory/active_directory.py
active_directory/entry_points.py
middleware_active_directory.egg-info/PKG-INFO
middleware_active_directory.egg-info/SOURCES.txt
middleware_active_directory.egg-info/dependency_links.txt
middleware_active_directory.egg-info/entry_points.txt
middleware_active_directory.egg-info/not-zip-safe
middleware_active_directory.egg-info/requires.txt
middleware_active_directory.egg-info/top_level.txt