Metadata-Version: 1.1
Name: middleware-active-directory
Version: 2.0
Summary: Middleware plugin for active directory
Home-page: UNKNOWN
Author: UNKNOWN
Author-email: probachai.yu@gmail.com
License: BSD
Platform: UNKNOWN
Classifier: Development Status :: 3 - Alpha
Classifier: Environment :: Web Environment
Classifier: Intended Audience :: Developers
Classifier: License :: OSI Approved :: BSD License
Classifier: Operating System :: OS Independent
Classifier: Programming Language :: Python :: 2
